holour/__init__.py
holour/config.py
holour/json_handler.py
holour/logging.py
holour/mqtt/__init__.py
holour/mqtt/client.py
holour/mqtt/config.py
holour/msg/__init__.py
holour/msg/force_torque.py
holour/msg/geometry.py
holour/msg/process.py
holour/msg/product.py
holour/msg/robot.py
holour/msg/script.py
holour/msg/status.py
holour/msg/task.py
tests/__init__.py
tests/test_config.py
tests/test_mqtt_client.py
tests/test_msg_force_torque.py
tests/test_msg_geometry.py
tests/test_msg_process.py
tests/test_msg_product.py
tests/test_msg_robot.py
tests/test_msg_script.py
tests/test_msg_status.py
tests/test_msg_task.py
holour-4.4.1.dist-info/METADATA
holour-4.4.1.dist-info/WHEEL
holour-4.4.1.dist-info/top_level.txt
holour-4.4.1.dist-info/RECORD
