Metadata-Version: 2.1
Name: holour
Version: 4.4.1
Summary: Collection of common data types
Home-page: https://gitlab.au.dk/hrc/common/holour
Author: Rasmus Lunding
Author-email: rlh@cs.au.dk
Classifier: Programming Language :: Python :: 3
Classifier: License :: OSI Approved :: MIT License
Classifier: Operating System :: OS Independent
Requires-Python: >=3.7
Requires-Dist: paho-mqtt (>=1.6.1)
Requires-Dist: PyYAML (>=6.0)
